googledriver/__init__.py
googledriver/cli.py
googledriver/downloader.py
googledriver/folder_downloader.py
googledriver/hub.py
googledriver-0.1.7.dist-info/LICENSE
googledriver-0.1.7.dist-info/METADATA
googledriver-0.1.7.dist-info/WHEEL
googledriver-0.1.7.dist-info/entry_points.txt
googledriver-0.1.7.dist-info/top_level.txt
googledriver-0.1.7.dist-info/RECORD
