Metadata-Version: 2.1
Name: googledriver
Version: 0.1.7
Summary: The Python package google drive facilitates access to files uploaded to Google Drive.
Home-page: https://github.com/DSDanielPark/google-driver
Author: parkminwoo
Author-email: parkminwoo1991@gmail.com
License: UNKNOWN
Keywords: Download,Googledrive
Platform: UNKNOWN
Classifier: Development Status :: 2 - Pre-Alpha
Classifier: Intended Audience :: Developers
Classifier: Natural Language :: English
Classifier: Programming Language :: Python
Classifier: Programming Language :: Python :: 3.6
Classifier: Programming Language :: Python :: 3.7
Classifier: Programming Language :: Python :: 3.8
Classifier: Programming Language :: Python :: 3.9
Classifier: Programming Language :: Python :: Implementation :: CPython
Requires-Python: >=3.6
License-File: LICENSE
Requires-Dist: filelock
Requires-Dist: requests[socks]
Requires-Dist: six
Requires-Dist: tqdm
Requires-Dist: beautifulsoup4
